utils_anviks-3.0.0.dist-info/RECORD
utils_anviks-3.0.0.dist-info/WHEEL
utils_anviks-3.0.0.dist-info/top_level.txt
utils_anviks-3.0.0.dist-info/METADATA
utils_anviks-3.0.0.dist-info/licenses/LICENCE
utils_anviks/functions.py
utils_anviks/grid.py
utils_anviks/cell.pyi
utils_anviks/cell.cpython-310-darwin.so
utils_anviks/__init__.py
utils_anviks/functions.pyi
utils_anviks/cell.c
utils_anviks/profiler.py
utils_anviks/decorators.py
