Metadata-Version: 2.4
Name: utils_anviks
Version: 3.0.0
Summary: A collection of utilities (mostly for Advent of Code)
Author-email: Andreas Marten Viks <andreasviks0@gmail.com>
Project-URL: Homepage, https://github.com/anviks/utils-anviks/
Project-URL: Issues, https://github.com/anviks/utils-anviks/issues
Project-URL: Changelog, https://github.com/anviks/utils-anviks/blob/master/CHANGELOG.md
Classifier: Programming Language :: Python :: 3
Classifier: Programming Language :: Python :: 3.10
Classifier: Programming Language :: Python :: 3.11
Classifier: Programming Language :: Python :: 3.12
Classifier: Programming Language :: Python :: 3.13
Classifier: License :: OSI Approved :: MIT License
Classifier: Operating System :: OS Independent
Requires-Python: >=3.10
License-File: LICENCE
Provides-Extra: dev
Requires-Dist: pytest; extra == "dev"
Requires-Dist: build; extra == "dev"
Requires-Dist: setuptools; extra == "dev"
Requires-Dist: wheel; extra == "dev"
Dynamic: license-file
